odoo/addons/fieldservice_isp_account/README.rst
odoo/addons/fieldservice_isp_account/__init__.py
odoo/addons/fieldservice_isp_account/__manifest__.py
odoo/addons/fieldservice_isp_account/data/time_products.xml
odoo/addons/fieldservice_isp_account/i18n/de.po
odoo/addons/fieldservice_isp_account/i18n/es.po
odoo/addons/fieldservice_isp_account/i18n/es_AR.po
odoo/addons/fieldservice_isp_account/i18n/es_CL.po
odoo/addons/fieldservice_isp_account/i18n/fieldservice_isp_account.pot
odoo/addons/fieldservice_isp_account/i18n/it.po
odoo/addons/fieldservice_isp_account/i18n/pt_BR.po
odoo/addons/fieldservice_isp_account/models/__init__.py
odoo/addons/fieldservice_isp_account/models/fsm_order.py
odoo/addons/fieldservice_isp_account/models/fsm_order_cost.py
odoo/addons/fieldservice_isp_account/models/fsm_person.py
odoo/addons/fieldservice_isp_account/readme/CONFIGURE.rst
odoo/addons/fieldservice_isp_account/readme/CONTRIBUTORS.rst
odoo/addons/fieldservice_isp_account/readme/CREDITS.rst
odoo/addons/fieldservice_isp_account/readme/DESCRIPTION.rst
odoo/addons/fieldservice_isp_account/readme/INSTALL.rst
odoo/addons/fieldservice_isp_account/readme/USAGE.rst
odoo/addons/fieldservice_isp_account/security/fsm_order_cost.xml
odoo/addons/fieldservice_isp_account/security/ir.model.access.csv
odoo/addons/fieldservice_isp_account/static/description/icon.png
odoo/addons/fieldservice_isp_account/static/description/index.html
odoo/addons/fieldservice_isp_account/tests/__init__.py
odoo/addons/fieldservice_isp_account/tests/test_isp_account.py
odoo/addons/fieldservice_isp_account/views/account.xml
odoo/addons/fieldservice_isp_account/views/fsm_order.xml
odoo/addons/fieldservice_isp_account/views/fsm_person.xml
odoo/addons/fieldservice_isp_account/views/hr_timesheet.xml
odoo_addon_fieldservice_isp_account-16.0.1.0.0.8.dist-info/METADATA
odoo_addon_fieldservice_isp_account-16.0.1.0.0.8.dist-info/WHEEL
odoo_addon_fieldservice_isp_account-16.0.1.0.0.8.dist-info/top_level.txt
odoo_addon_fieldservice_isp_account-16.0.1.0.0.8.dist-info/RECORD
