Metadata-Version: 2.1
Name: odoo-addon-fieldservice_isp_account
Version: 16.0.1.0.0.8
Summary: Invoice Field Service orders based on employee time or contractor costs
Home-page: https://github.com/OCA/field-service
Author: Open Source Integrators, Odoo Community Association (OCA)
Author-email: support@odoo-community.org
License: AGPL-3
Classifier: Programming Language :: Python
Classifier: Framework :: Odoo
Classifier: Framework :: Odoo :: 16.0
Classifier: License :: OSI Approved :: GNU Affero General Public License v3
Classifier: Development Status :: 4 - Beta
Requires-Python: >=3.10
Requires-Dist: odoo-addon-fieldservice-account-analytic<16.1dev,>=16.0dev
Requires-Dist: odoo-addon-fieldservice-project<16.1dev,>=16.0dev
Requires-Dist: odoo<16.1dev,>=16.0a
